{"per_page":10,"total":4,"current":2,"data":[{"title":"使用Spring Cloud Feign上传文件","date":"2020-09-06T23:00:00.000Z","date_formatted":{"ll":"2020年9月6日","L":"2020/09/06","MM-DD":"09-06"},"excerpt":"<p>使用Spring Cloud Feign上传文件，早期的Spring Cloud中，Feign本身是没有上传文件的能力的，要想实现这一点，需要自己编写<code>Encoder</code>去实现上传。现在，Feign官方提供了子项目<a href=\"https://github.com/OpenFeign/feign-form\" target=\"_blank\">feign-form</a>，其中实现了上传所需的<code>Encoder</code>。</p>","link":"2020/09/feign-upload","tags":["Spring-Cloud","Spring-Cloud-Alibaba"],"categories":["Java"]},{"title":"IDEA中的Web项目移动到Eclipse","date":"2020-06-01T22:19:00.000Z","date_formatted":{"ll":"2020年6月1日","L":"2020/06/01","MM-DD":"06-01"},"excerpt":"","link":"2020/06/ideaproj-to-eclipse","tags":["IntelliJ IDEA","eclipse"]},{"title":"Mac OS下安装和配置Maven","date":"2020-05-11T14:52:00.000Z","date_formatted":{"ll":"2020年5月11日","L":"2020/05/11","MM-DD":"05-11"},"excerpt":"","link":"2020/05/macos-maven","categories":["Java"]},{"title":"设置eclipse格式化时不对注释进行格式化","date":"2020-04-26T15:12:00.000Z","date_formatted":{"ll":"2020年4月26日","L":"2020/04/26","MM-DD":"04-26"},"excerpt":"","link":"2020/04/eclipse-format-code","tags":["eclipse"]},{"title":"阶段性学习笔记","date":"2020-04-21T21:10:00.000Z","date_formatted":{"ll":"2020年4月21日","L":"2020/04/21","MM-DD":"04-21"},"excerpt":"","link":"2020/04/java-note"},{"title":"eclipse实现自动补全","date":"2020-04-21T15:07:00.000Z","date_formatted":{"ll":"2020年4月21日","L":"2020/04/21","MM-DD":"04-21"},"excerpt":"<p>eclipse设置自动补全：</p>","link":"2020/04/eclipse-auto-completion","tags":["eclipse"],"categories":["Java"]},{"title":"Java编译运行时报错尝试解决办法","date":"2020-04-20T18:02:00.000Z","date_formatted":{"ll":"2020年4月20日","L":"2020/04/20","MM-DD":"04-20"},"excerpt":"","link":"2020/04/java-compile-error","tags":["eclipse"]},{"title":"Linux下的Vim使用教程","date":"2020-04-11T00:00:00.000Z","date_formatted":{"ll":"2020年4月11日","L":"2020/04/11","MM-DD":"04-11"},"excerpt":"","link":"2020/04/vim-help","tags":["Vim"]},{"title":"L2TP/IPSec一键安装脚本","date":"2020-03-12T21:00:00.000Z","date_formatted":{"ll":"2020年3月12日","L":"2020/03/12","MM-DD":"03-12"},"excerpt":"","link":"2020/03/l2tp"},{"title":"入手日版Nintendo Switch","date":"2020-01-29T12:49:00.000Z","date_formatted":{"ll":"2020年1月29日","L":"2020/01/29","MM-DD":"01-29"},"excerpt":"","link":"2020/01/Nintendo-Switch","tags":["Nintendo Switch"],"categories":["生活"]}]}